pyrainbird/__init__.py
pyrainbird/async_client.py
pyrainbird/const.py
pyrainbird/data.py
pyrainbird/encryption.py
pyrainbird/exceptions.py
pyrainbird/rainbird.py
pyrainbird/timeline.py
pyrainbird/resources/__init__.py
pyrainbird/resources/models.yaml
pyrainbird/resources/sipcommands.yaml
pyrainbird-6.0.2.dist-info/LICENSE
pyrainbird-6.0.2.dist-info/METADATA
pyrainbird-6.0.2.dist-info/WHEEL
pyrainbird-6.0.2.dist-info/top_level.txt
pyrainbird-6.0.2.dist-info/RECORD
