Metadata-Version: 2.1
Name: pyrainbird
Version: 6.0.2
Summary: Rain Bird Controller
Home-page: https://github.com/allenporter/pyrainbird
Author: J.J.Barrancos
Author-email: jordy@fusion-ict.nl
License: MIT
Keywords: Rain Bird
Requires-Python: >=3.11
License-File: LICENSE
Requires-Dist: pycryptodome >=3.16.0
Requires-Dist: requests >=2.22.0
Requires-Dist: PyYAML >=5.4
Requires-Dist: mashumaro >=3.12
Requires-Dist: python-dateutil >=2.8.2
Requires-Dist: ical >=4.2.9
Requires-Dist: aiohttp-retry >=2.8.3
